ga_secret_generator/__init__.py
ga_secret_generator-0.1.3.dist-info/LICENSE
ga_secret_generator-0.1.3.dist-info/METADATA
ga_secret_generator-0.1.3.dist-info/WHEEL
ga_secret_generator-0.1.3.dist-info/entry_points.txt
ga_secret_generator-0.1.3.dist-info/top_level.txt
ga_secret_generator-0.1.3.dist-info/RECORD
