Metadata-Version: 2.1
Name: ga-secret-generator
Version: 0.1.3
Summary: generats a google authenticator totp secret
Home-page: https://github.com/andrekeller/ga-secret-generator
Author: Andre Keller
Author-email: andre.keller@vshn.ch
License: BSD
Platform: UNKNOWN
Classifier: Development Status :: 4 - Beta
Classifier: Environment :: Console
Classifier: Intended Audience :: System Administrators
Classifier: License :: OSI Approved :: BSD License
Classifier: Operating System :: Unix
Classifier: Programming Language :: Python :: 3 :: Only
Classifier: Topic :: System :: Systems Administration
Requires-Python: >=3.4
Requires-Dist: pyqrcode
Requires-Dist: pypng
